odoo/addons/mail_template_multi_attachment/README.rst
odoo/addons/mail_template_multi_attachment/__init__.py
odoo/addons/mail_template_multi_attachment/__manifest__.py
odoo/addons/mail_template_multi_attachment/i18n/it.po
odoo/addons/mail_template_multi_attachment/i18n/mail_template_multi_attachment.pot
odoo/addons/mail_template_multi_attachment/models/__init__.py
odoo/addons/mail_template_multi_attachment/models/mail_template.py
odoo/addons/mail_template_multi_attachment/models/mail_template_report.py
odoo/addons/mail_template_multi_attachment/readme/CONFIGURE.rst
odoo/addons/mail_template_multi_attachment/readme/CONTRIBUTORS.rst
odoo/addons/mail_template_multi_attachment/readme/DESCRIPTION.rst
odoo/addons/mail_template_multi_attachment/readme/USAGE.rst
odoo/addons/mail_template_multi_attachment/security/mail_template_report.xml
odoo/addons/mail_template_multi_attachment/static/description/icon.png
odoo/addons/mail_template_multi_attachment/static/description/index.html
odoo/addons/mail_template_multi_attachment/tests/__init__.py
odoo/addons/mail_template_multi_attachment/tests/test_mail_template.py
odoo/addons/mail_template_multi_attachment/views/mail_template.xml
odoo/addons/mail_template_multi_attachment/views/mail_template_report.xml
odoo_addon_mail_template_multi_attachment-16.0.1.0.0.4.dist-info/METADATA
odoo_addon_mail_template_multi_attachment-16.0.1.0.0.4.dist-info/WHEEL
odoo_addon_mail_template_multi_attachment-16.0.1.0.0.4.dist-info/top_level.txt
odoo_addon_mail_template_multi_attachment-16.0.1.0.0.4.dist-info/RECORD
